Metadata-Version: 2.1
Name: pruebalibreria
Version: 0.2.1.1
Summary: Metodo MTR
Author-email: ramosjack066@gmail.com
License: MIT
Keywords: testing,logging,example
